.gitignore
LICENSE
README.md
pyproject.toml
.github/workflows/python-publish.yml
docs/Makefile
docs/abbrev_long.bib
docs/conf.py
docs/conf_spec.py
docs/index.rst
docs/make.bat
docs/references.bib
docs/_static/styles/my_theme.css
docs/_templates/autoapi/index.rst
docs/_templates/autoapi/python/attribute.rst
docs/_templates/autoapi/python/class.rst
docs/_templates/autoapi/python/data.rst
docs/_templates/autoapi/python/exception.rst
docs/_templates/autoapi/python/function.rst
docs/_templates/autoapi/python/method.rst
docs/_templates/autoapi/python/module.rst
docs/_templates/autoapi/python/package.rst
docs/_templates/autoapi/python/property.rst
src/simplepyutils/__init__.py
src/simplepyutils/_version.py
src/simplepyutils/argparse.py
src/simplepyutils/file_io.py
src/simplepyutils/itertools.py
src/simplepyutils/misc.py
src/simplepyutils/picklecachefun.py
src/simplepyutils/strings.py
src/simplepyutils/throttledpool.py
src/simplepyutils.egg-info/PKG-INFO
src/simplepyutils.egg-info/SOURCES.txt
src/simplepyutils.egg-info/dependency_links.txt
src/simplepyutils.egg-info/requires.txt
src/simplepyutils.egg-info/top_level.txt